teneva_ht_jax/__init__.py
teneva_ht_jax/act_one.py
teneva_ht_jax/gd.py
teneva_ht_jax/tensors.py
teneva_ht_jax/transformation.py
teneva_ht_jax/vis.py
teneva_ht_jax-0.1.2.dist-info/LICENSE.txt
teneva_ht_jax-0.1.2.dist-info/METADATA
teneva_ht_jax-0.1.2.dist-info/WHEEL
teneva_ht_jax-0.1.2.dist-info/top_level.txt
teneva_ht_jax-0.1.2.dist-info/RECORD
