Metadata-Version: 2.1
Name: teneva-ht-jax
Version: 0.1.2
Summary: Compact implementation of basic operations in the Hierarchical Tucker (HT) format for approximation and sampling from multidimensional arrays and multivariate functions
Home-page: https://github.com/AndreiChertkov/teneva_ht_jax
Author: Andrei Chertkov
Author-email: andre.chertkov@gmail.com
License: MIT
Project-URL: Source, https://github.com/AndreiChertkov/teneva_ht_jax
Keywords: low-rank representation tensor hierarchical tucker approximation
Classifier: Development Status :: 3 - Alpha
Classifier: License :: OSI Approved :: MIT License
Classifier: Topic :: Scientific/Engineering
Classifier: Topic :: Scientific/Engineering :: Mathematics
Classifier: Topic :: Scientific/Engineering :: Information Analysis
Classifier: Topic :: Scientific/Engineering :: Artificial Intelligence
Classifier: Intended Audience :: Science/Research
Classifier: Operating System :: OS Independent
Classifier: Programming Language :: Python :: 3
Classifier: Programming Language :: Python :: 3 :: Only
Classifier: Programming Language :: Python :: 3.8
Classifier: Programming Language :: Python :: 3.9
Classifier: Framework :: Jupyter
Requires-Python: >=3.8
License-File: LICENSE.txt
Requires-Dist: jax[cpu] (>=0.4.3)
Requires-Dist: numpy (>=1.22)
Requires-Dist: scipy (>=1.8)
Requires-Dist: opt-einsum (>=3.3)
Requires-Dist: optax (>=0.1.5)
